golem_reputation/__init__.py
golem_reputation/entrypoints/__init__.py
golem_reputation/entrypoints/cli/__init__.py
golem_reputation/entrypoints/cli/database.py
golem_reputation/entrypoints/cli/main.py
golem_reputation/entrypoints/cli/reputation.py
golem_reputation/entrypoints/cli/utils.py
golem_reputation/exceptions.py
golem_reputation/migrations/models/0_20240311095546_init.py
golem_reputation/migrations/models/2_20240312164006_update.py
golem_reputation/migrations/models/3_20240314085535_blacklisted_until_index.py
golem_reputation/models.py
golem_reputation/plugins/__init__.py
golem_reputation/plugins/blacklist.py
golem_reputation/plugins/score.py
golem_reputation/service.py
golem_reputation/settings.py
golem_reputation/updater.py
golem_workers/__init__.py
golem_workers/budgets.py
golem_workers/cluster/__init__.py
golem_workers/cluster/cluster.py
golem_workers/cluster/manager_stack.py
golem_workers/cluster/node.py
golem_workers/containers.py
golem_workers/context.py
golem_workers/entrypoints/__init__.py
golem_workers/entrypoints/web/__init__.py
golem_workers/entrypoints/web/application.py
golem_workers/entrypoints/web/dependencies.py
golem_workers/entrypoints/web/endpoints.py
golem_workers/entrypoints/web/main.py
golem_workers/events.py
golem_workers/exceptions.py
golem_workers/golem.py
golem_workers/models.py
golem_workers/payloads.py
golem_workers/services/README.md
golem_workers/services/__init__.py
golem_workers/services/clusters.py
golem_workers/services/interfaces.py
golem_workers/services/nodes.py
golem_workers/services/port_allocation.py
golem_workers/services/port_allocation_service.py
golem_workers/services/proposals.py
golem_workers/services/types.py
golem_workers/settings.py
golem_workers/sidecars.py
golem_workers/utils.py
golem_workers/work.py
golem_workers-0.5.0.dist-info/LICENSE
golem_workers-0.5.0.dist-info/METADATA
golem_workers-0.5.0.dist-info/WHEEL
golem_workers-0.5.0.dist-info/entry_points.txt
golem_workers-0.5.0.dist-info/RECORD
