Metadata-Version: 2.3
Name: golem-workers
Version: 0.5.0
Summary: Golem Workers is an API providing direct and high-level access to CPU and GPU resources on the Golem Network.
Author: Golem Factory
Author-email: contact@golem.network
Requires-Python: >=3.10,<4.0
Classifier: Programming Language :: Python :: 3
Classifier: Programming Language :: Python :: 3.10
Classifier: Programming Language :: Python :: 3.11
Classifier: Programming Language :: Python :: 3.12
Classifier: Programming Language :: Python :: 3.13
Requires-Dist: aerich (>=0.7.2,<0.8.0)
Requires-Dist: appdirs (>=1.4.4,<2.0.0)
Requires-Dist: dependency-injector (>=4.41.0,<5.0.0)
Requires-Dist: dpath (>=2.1.6,<3.0.0)
Requires-Dist: fastapi (>=0.111.0,<0.112.0)
Requires-Dist: golem-core (>=0.8,<0.9)
Requires-Dist: golem-node (>=0.17.0,<0.18.0)
Requires-Dist: prettytable (>=3.10.2,<4.0.0)
Requires-Dist: pydantic-settings (>=2.3.1,<3.0.0)
Requires-Dist: tortoise-orm (>=0.21.5,<0.22.0)
Requires-Dist: websocat (>=1.13.0,<2.0.0)
